[
    {
        "data": "2025-08-07 15:48:26",
        "nome": "Miguel",
        "email": "guelpohlmann@gmail.com",
        "telefone": "51999298592",
        "mensagem": "mifbiffr"
    },
    {
        "data": "2025-08-07 15:53:21",
        "nome": "Miguel",
        "email": "guelpohlmann@gmail.com",
        "telefone": "51999298592",
        "mensagem": "mifbiffr"
    },
    {
        "data": "2025-08-07 15:53:40",
        "nome": "Miguel",
        "email": "guelpohlmann@gmail.com",
        "telefone": "51999298592",
        "mensagem": "ttttttttttttttttttttttttttttttt"
    },
    {
        "data": "2025-08-07 15:56:02",
        "nome": "Miguel",
        "email": "guelpohlmann@gmail.com",
        "telefone": "51999298592",
        "mensagem": "mirnvfbvf"
    },
    {
        "data": "2025-08-07 15:58:03",
        "nome": "Miguel",
        "email": "guelpohlmann@gmail.com",
        "telefone": "51999298592",
        "mensagem": "mirnvfbvf"
    },
    {
        "data": "2025-08-07 18:57:27",
        "nome": "Miguel",
        "email": "guelpohlmann@gmail.com",
        "telefone": "51999298592",
        "mensagem": "oi tudo bem?"
    },
    {
        "data": "2025-08-08 13:56:31",
        "nome": "Miguel",
        "email": "guelpohlmann@gmail.com",
        "telefone": "51999298592",
        "mensagem": "oi"
    },
    {
        "data": "2025-08-08 13:57:17",
        "nome": "Miguel",
        "email": "guelpohlmann@gmail.com",
        "telefone": "51999298592",
        "mensagem": "oi"
    }
]